[
  {
    "model": "market_no_vig",
    "matches": 6582,
    "accuracy": 0.5404132482528107,
    "log_loss": 0.9696929565057599,
    "brier": 0.576789210280839,
    "exact_score_hit_rate": null,
    "bets": 0,
    "roi": 0.0,
    "profit": 0.0,
    "max_drawdown": 0.0,
    "ending_bankroll": 1000.0
  },
  {
    "model": "xgboost_conservative_all",
    "matches": 6582,
    "accuracy": 0.5341841385597083,
    "log_loss": 0.9776507159509743,
    "brier": 0.5813087303642264,
    "exact_score_hit_rate": null,
    "bets": 1300,
    "roi": -0.045256885692306036,
    "profit": -775.27496935205,
    "max_drawdown": -0.8934607452717988,
    "ending_bankroll": 224.72503064795052
  },
  {
    "model": "xgboost_conservative_all_poisson_blend",
    "matches": 6582,
    "accuracy": 0.5332725615314494,
    "log_loss": 0.979429214730981,
    "brier": 0.58261312461673,
    "exact_score_hit_rate": null,
    "bets": 2143,
    "roi": -0.07122319674302993,
    "profit": -914.701587530481,
    "max_drawdown": -0.9221713479985548,
    "ending_bankroll": 85.29841246951865
  },
  {
    "model": "xgboost_current_all_poisson_blend",
    "matches": 6582,
    "accuracy": 0.5303859009419629,
    "log_loss": 0.9837417966024742,
    "brier": 0.5852214955369216,
    "exact_score_hit_rate": null,
    "bets": 3077,
    "roi": -0.04190169556813834,
    "profit": -882.0453407935026,
    "max_drawdown": -0.9265527612735386,
    "ending_bankroll": 117.95465920649758
  },
  {
    "model": "xgboost_current_all",
    "matches": 6582,
    "accuracy": 0.531145548465512,
    "log_loss": 0.9884618809641585,
    "brier": 0.5877311104665316,
    "exact_score_hit_rate": null,
    "bets": 3371,
    "roi": -0.019058970138367323,
    "profit": -914.4145739766338,
    "max_drawdown": -0.9602909382231624,
    "ending_bankroll": 85.5854260233649
  },
  {
    "model": "logistic_all_poisson_blend",
    "matches": 6582,
    "accuracy": 0.5183834700698876,
    "log_loss": 0.9906613854915823,
    "brier": 0.5903073195459784,
    "exact_score_hit_rate": null,
    "bets": 4793,
    "roi": -0.06398433201800373,
    "profit": -987.2143013459681,
    "max_drawdown": -0.9884132848300526,
    "ending_bankroll": 12.785698654031773
  },
  {
    "model": "random_forest_all_poisson_blend",
    "matches": 6582,
    "accuracy": 0.5186873290793071,
    "log_loss": 0.9911666932226056,
    "brier": 0.5904528649328327,
    "exact_score_hit_rate": null,
    "bets": 4409,
    "roi": -0.10460293423457469,
    "profit": -985.6118560524482,
    "max_drawdown": -0.9870127854688626,
    "ending_bankroll": 14.38814394755245
  },
  {
    "model": "elo_poisson_blend",
    "matches": 6582,
    "accuracy": 0.5176238225463385,
    "log_loss": 0.9960997421995158,
    "brier": 0.5944805223017476,
    "exact_score_hit_rate": null,
    "bets": 3202,
    "roi": -0.11802156235726541,
    "profit": -999.4180937432054,
    "max_drawdown": -0.999480427391805,
    "ending_bankroll": 0.5819062567943687
  },
  {
    "model": "random_forest_all",
    "matches": 6582,
    "accuracy": 0.5113947128532361,
    "log_loss": 0.9963961093116447,
    "brier": 0.5944900903961726,
    "exact_score_hit_rate": null,
    "bets": 5308,
    "roi": -0.06840319109981785,
    "profit": -996.6991559044418,
    "max_drawdown": -0.9976194900718038,
    "ending_bankroll": 3.3008440955572356
  },
  {
    "model": "extra_trees_all_poisson_blend",
    "matches": 6582,
    "accuracy": 0.5197508356122759,
    "log_loss": 0.9964733658593236,
    "brier": 0.5943930546080347,
    "exact_score_hit_rate": null,
    "bets": 4514,
    "roi": -0.08493891321817401,
    "profit": -992.2323655970667,
    "max_drawdown": -0.9947206350956287,
    "ending_bankroll": 7.76763440293521
  },
  {
    "model": "hist_gradient_all_poisson_blend",
    "matches": 6582,
    "accuracy": 0.5252202977818292,
    "log_loss": 0.9964967323429907,
    "brier": 0.5921952248862873,
    "exact_score_hit_rate": null,
    "bets": 4116,
    "roi": -0.01666370635314068,
    "profit": -783.8787001767904,
    "max_drawdown": -0.9532151280781035,
    "ending_bankroll": 216.12129982321107
  },
  {
    "model": "elo_baseline",
    "matches": 6582,
    "accuracy": 0.5159525979945305,
    "log_loss": 0.9975537806981022,
    "brier": 0.5955482198716014,
    "exact_score_hit_rate": null,
    "bets": 3312,
    "roi": -0.1560763283330331,
    "profit": -999.7665838344863,
    "max_drawdown": -0.9998003844900014,
    "ending_bankroll": 0.2334161655140404
  },
  {
    "model": "xgboost_conservative_no_market_poisson_blend",
    "matches": 6582,
    "accuracy": 0.5153448799756912,
    "log_loss": 0.9984684040902149,
    "brier": 0.5957130252553274,
    "exact_score_hit_rate": null,
    "bets": 3947,
    "roi": -0.11835674422266221,
    "profit": -999.8365603497393,
    "max_drawdown": -0.9998570225934351,
    "ending_bankroll": 0.16343965026056484
  },
  {
    "model": "logistic_all",
    "matches": 6582,
    "accuracy": 0.4971133394105135,
    "log_loss": 1.0001851679998484,
    "brier": 0.5972341063919047,
    "exact_score_hit_rate": null,
    "bets": 5740,
    "roi": -0.1366001833861868,
    "profit": -999.614335638223,
    "max_drawdown": -0.9997113793036789,
    "ending_bankroll": 0.38566436177717905
  },
  {
    "model": "xgboost_conservative_no_market",
    "matches": 6582,
    "accuracy": 0.5186873290793071,
    "log_loss": 1.0002149092459949,
    "brier": 0.5967208781858355,
    "exact_score_hit_rate": null,
    "bets": 3972,
    "roi": -0.13583645429041868,
    "profit": -999.943821685688,
    "max_drawdown": -0.9999476526678622,
    "ending_bankroll": 0.05617831431281394
  },
  {
    "model": "extra_trees_all",
    "matches": 6582,
    "accuracy": 0.5079003342449103,
    "log_loss": 1.0014676996462926,
    "brier": 0.5984653066684007,
    "exact_score_hit_rate": null,
    "bets": 5759,
    "roi": -0.07221924118930163,
    "profit": -999.110806761683,
    "max_drawdown": -0.9992715782710964,
    "ending_bankroll": 0.8891932383169834
  },
  {
    "model": "logistic_no_market_poisson_blend",
    "matches": 6582,
    "accuracy": 0.5042540261318748,
    "log_loss": 1.012909929281527,
    "brier": 0.6039946903723541,
    "exact_score_hit_rate": null,
    "bets": 4793,
    "roi": -0.14138990197925672,
    "profit": -999.0231834566704,
    "max_drawdown": -0.9990718200842547,
    "ending_bankroll": 0.9768165433304588
  },
  {
    "model": "hist_gradient_all",
    "matches": 6582,
    "accuracy": 0.5161045274992404,
    "log_loss": 1.0194226348653945,
    "brier": 0.6027027172793926,
    "exact_score_hit_rate": null,
    "bets": 4699,
    "roi": -0.02407704915161958,
    "profit": -943.0779820772599,
    "max_drawdown": -0.9563065142589409,
    "ending_bankroll": 56.92201792274189
  },
  {
    "model": "hist_gradient_no_market_poisson_blend",
    "matches": 6582,
    "accuracy": 0.5120024308720753,
    "log_loss": 1.0198549618526855,
    "brier": 0.6070170388106867,
    "exact_score_hit_rate": null,
    "bets": 4849,
    "roi": -0.040449898376357846,
    "profit": -993.1280169185468,
    "max_drawdown": -0.9941465714171628,
    "ending_bankroll": 6.871983081452791
  },
  {
    "model": "logistic_no_market",
    "matches": 6582,
    "accuracy": 0.4905803707079915,
    "log_loss": 1.0218129997703436,
    "brier": 0.609691415007965,
    "exact_score_hit_rate": null,
    "bets": 5685,
    "roi": -0.08008032321791216,
    "profit": -999.4148204803125,
    "max_drawdown": -0.9994439571268644,
    "ending_bankroll": 0.5851795196878432
  },
  {
    "model": "poisson_goals",
    "matches": 6582,
    "accuracy": 0.5025828015800669,
    "log_loss": 1.0234683864731968,
    "brier": 0.6108486185078733,
    "exact_score_hit_rate": null,
    "bets": 4914,
    "roi": -0.1265342997882251,
    "profit": -999.189502937417,
    "max_drawdown": -0.9995577899588617,
    "ending_bankroll": 0.810497062582886
  },
  {
    "model": "hist_gradient_no_market",
    "matches": 6582,
    "accuracy": 0.5085080522637496,
    "log_loss": 1.045148786676209,
    "brier": 0.6184171325596963,
    "exact_score_hit_rate": null,
    "bets": 5194,
    "roi": -0.024822498548357153,
    "profit": -997.7121886242888,
    "max_drawdown": -0.9987863522682248,
    "ending_bankroll": 2.2878113757135936
  }
]